inverse_text_normalization/__init__.py
inverse_text_normalization/run_predict.py
inverse_text_normalization/asm/__init__.py
inverse_text_normalization/asm/clean_eval_data.py
inverse_text_normalization/asm/data_loader_utils.py
inverse_text_normalization/asm/graph_utils.py
inverse_text_normalization/asm/inverse_normalize.py
inverse_text_normalization/asm/run_evaluate.py
inverse_text_normalization/asm/run_predict.py
inverse_text_normalization/asm/token_parser.py
inverse_text_normalization/asm/utils.py
inverse_text_normalization/asm/data/__init__.py
inverse_text_normalization/asm/data/currency.tsv
inverse_text_normalization/asm/data/magnitudes.tsv
inverse_text_normalization/asm/data/measurements.tsv
inverse_text_normalization/asm/data/months.tsv
inverse_text_normalization/asm/data/sentence_boundary_exceptions.txt
inverse_text_normalization/asm/data/suppletive.tsv
inverse_text_normalization/asm/data/time_suffix.tsv
inverse_text_normalization/asm/data/time_zone.tsv
inverse_text_normalization/asm/data/whitelist.tsv
inverse_text_normalization/asm/data/numbers/__init__.py
inverse_text_normalization/asm/data/numbers/crore.tsv
inverse_text_normalization/asm/data/numbers/digit.tsv
inverse_text_normalization/asm/data/numbers/hundred.tsv
inverse_text_normalization/asm/data/numbers/lakh.tsv
inverse_text_normalization/asm/data/numbers/teen.tsv
inverse_text_normalization/asm/data/numbers/tens.tsv
inverse_text_normalization/asm/data/numbers/thousands.tsv
inverse_text_normalization/asm/data/numbers/ties.tsv
inverse_text_normalization/asm/data/numbers/zero.tsv
inverse_text_normalization/asm/data/ordinals/__init__.py
inverse_text_normalization/asm/data/ordinals/digit.tsv
inverse_text_normalization/asm/data/ordinals/teen.tsv
inverse_text_normalization/asm/taggers/__init__.py
inverse_text_normalization/asm/taggers/cardinal.py
inverse_text_normalization/asm/taggers/date.py
inverse_text_normalization/asm/taggers/decimal.py
inverse_text_normalization/asm/taggers/electronic.py
indic_punct-2.1.4.dist-info/LICENSE
indic_punct-2.1.4.dist-info/METADATA
indic_punct-2.1.4.dist-info/WHEEL
indic_punct-2.1.4.dist-info/top_level.txt
indic_punct-2.1.4.dist-info/RECORD
