Metadata-Version: 2.1
Name: indic-punct
Version: 2.1.4
Summary: Punctuation and inverse text normalization for Indic languages and English
Home-page: https://github.com/Open-Speech-EkStep/indic-punct
License: UNKNOWN
Keywords: nlp,punctuation,Indic languages,deep learning
Platform: UNKNOWN
Classifier: Development Status :: 3 - Alpha
Classifier: Intended Audience :: Developers
Classifier: Intended Audience :: Education
Classifier: Intended Audience :: Science/Research
Classifier: Topic :: Scientific/Engineering :: Artificial Intelligence
Classifier: Topic :: Text Processing :: Linguistic
Classifier: License :: OSI Approved :: MIT License
Classifier: Programming Language :: Python :: 3.8
Requires-Python: >=3.6, <4
License-File: LICENSE
Requires-Dist: wget
Requires-Dist: Cython
Requires-Dist: certifi (==2020.12.5)
Requires-Dist: inflect (==5.3.0)
Requires-Dist: numpy (==1.20.2)
Requires-Dist: pandas (==1.2.4)
Requires-Dist: python-dateutil (==2.8.1)
Requires-Dist: pytz (==2021.1)
Requires-Dist: six (==1.15.0)
Requires-Dist: tqdm (==4.60.0)
Requires-Dist: torch (==1.7.1)
Requires-Dist: scipy (==1.5.4)
Requires-Dist: sentencepiece (==0.1.94)
Requires-Dist: tokenizers (==0.10.1)
Requires-Dist: torchvision (==0.8.2)
Requires-Dist: transformers (<=4.3.2,>=0.9.4)
Requires-Dist: indic-nlp-library (==0.81)
Requires-Dist: nemo-toolkit[all] (==v1.0.2)
Requires-Dist: pynini (==2.1.4)
